nagios_plugin/__init__.py
nagios_plugin/plugin.py
sld.nagios_plugin-0.0.6.dist-info/AUTHORS.rst
sld.nagios_plugin-0.0.6.dist-info/LICENSE
sld.nagios_plugin-0.0.6.dist-info/METADATA
sld.nagios_plugin-0.0.6.dist-info/WHEEL
sld.nagios_plugin-0.0.6.dist-info/top_level.txt
sld.nagios_plugin-0.0.6.dist-info/RECORD
